{"className":"14EKA","parseError":false,"titles":["M\u00e5ndag 12\/12","Tisdag 13\/12","Onsdag 14\/12","Torsdag 15\/12","Fredag 16\/12"],"lessons":[{"startTime":"08:40","endTime":"09:40","rows":["RELREL01","RELREL01-14EKA","St  A34"],"location":"A34","day":0},{"startTime":"09:50","endTime":"10:50","rows":["JURR\u00c4T0","JURR\u00c4T0-14EKA","Wmn  A12"],"location":"A12","day":0},{"startTime":"12:15","endTime":"13:20","rows":["MATMAT03b","MATMAT03b-14EKA","Mts  A13"],"location":"A13","day":0},{"startTime":"13:35","endTime":"15:30","rows":["SVERET0","SVERET0-14EKA","Hig  C112"],"location":"C112","day":0},{"startTime":"08:30","endTime":"10:30","rows":["ENGENG07 ENGENG07-16IndO:a","A14","Oln","ENGENG07 ENGENG07-16IndO:b","Bw","C211","ENGENG07 ENGENG07-16IndO:c","Ks","A12","ENGENG07 ENGENG07-16IndO:d","Har","A22","ENGENG07 ENGENG07-16IndO:e","Dg","C113","ENGENG07 ENGENG07-16IndO:f","B43","Rhn","FOTFOT01 FOTFOT01-16IndO","Srt","B45","IDRIDO01 IDRIDO01-16IndO","Ols","JURPRI0 JURPRI0-16IndO","Wmn","C213","LEDLED0 LEDLED0-16IndO","A11","Hmn","MATMAT03b MATMAT03b-16IndO","C312","Ct","MATMAT05 MATMAT05-16IndO","Han","A34","PSKPSY01 PSKPSY01-16IndO","Axn","A21"],"location":"A21","day":2},{"startTime":"08:30","endTime":"10:30","rows":["NAKNAK02","NAKNAK02-16IndO","Tg  B44"],"location":"B44","day":2},{"startTime":"11:00","endTime":"11:55","rows":["JURR\u00c4T0","JURR\u00c4T0-14EKA","Wmn  C212"],"location":"C212","day":2},{"startTime":"13:15","endTime":"14:10","rows":["GYAREK","GYAREK-14EKA","Wmn  C212"],"location":"C212","day":2},{"startTime":"14:15","endTime":"15:15","rows":["GYAREK","GYAREK-14EKA","Wmn  C212"],"location":"C212","day":2},{"startTime":"15:25","endTime":"16:30","rows":["SVESVE03","SVESVE03-14EKA","Hig  C114"],"location":"C114","day":2},{"startTime":"09:45","endTime":"11:00","rows":["MATMAT03b","MATMAT03b-14EKA","Mts  A13"],"location":"A13","day":3},{"startTime":"12:15","endTime":"13:25","rows":["SVESVE03","SVESVE03-14EKA","Hig  C114"],"location":"C114","day":3},{"startTime":"13:40","endTime":"14:35","rows":["PSKPSY01","PSKPSY01-14EKA","St  A34"],"location":"A34","day":3},{"startTime":"15:00","endTime":"17:00","rows":["ENGENG07 ENGENG07-16IndT:a","Oln","A14","ENGENG07 ENGENG07-16IndT:b","Bw","C211","ENGENG07 ENGENG07-16IndT:c","A35","Rhn","ENGENG07 ENGENG07-16IndT:d","Wm","A25","F\u00d6RF\u00d6R01 F\u00d6RF\u00d6R01-16IndT","Sst","A31","HUMHUM00S HUMHUM00S-16IndT","A21","Bg","KOSFIL0 KOSFIL0-16IndT","Be","C311","MATMAT03b MATMAT03b-16IndT","C313","Mts","MATMAT05 MATMAT05-16IndT:a","Brd","A22","MATMAT05 MATMAT05-16IndT:b","My","A34","MERMEE01 MERMEE01-16INDT","A11","Hmn","MUSK\u00d6S01 MUSK\u00d6S01-16IndT","C41","Rh","SVERET0 SVERET0-16IndT","C22","Ni"],"location":"Ni","day":3},{"startTime":"08:30","endTime":"09:30","rows":["SVESVE03","SVESVE03-14EKSA","At  A21"],"location":"A21","day":4},{"startTime":"09:50","endTime":"10:50","rows":["PSKPSY01","PSKPSY01-14EKA","St  A13"],"location":"A13","day":4},{"startTime":"11:00","endTime":"11:55","rows":["RELREL01","RELREL01-14EKA","St  A13"],"location":"A13","day":4},{"startTime":"10:15","endTime":"12:15","rows":["ma3b, sal A13, Teresa"],"day":1}]}